sensio_lib/__init__.py
sensio_lib/const.py
sensio_lib/hub.py
sensio_lib/light.py
sensio_lib/light_state.py
sensio_lib/socket_manager.py
sensio_lib-0.1.0.dist-info/METADATA
sensio_lib-0.1.0.dist-info/WHEEL
sensio_lib-0.1.0.dist-info/RECORD
