Metadata-Version: 2.4
Name: sensio-lib
Version: 0.1.0
Requires-Python: ~=3.10
Requires-Dist: pytest<9,>=8.3.3
Requires-Dist: requests<3,>=2.32.3
